{
    "Description" : {
        "Id" : "art-girl-art-Sci-Fi-cat-1908354_cr",
        "Name" : "art-girl-art-Sci-Fi-cat-1908354_cr",
        "Details" : "Random",
        "Icon" : "art-girl-art-Sci-Fi-cat-1908354_cr"
    },
    "ID" : "art-girl-art-Sci-Fi-cat-1908354_cr",
    "backgroundColor" : {
        "r" : 0,
        "g" : 0,
        "b" : 0,
        "a" : 0
    },
    "headMesh" : 0.5,
    "hairMesh" : 4,
    "beardMesh" : 0,
    "suitMesh" : 2,
    "scar" : 0,
    "lightRig" : 5,
    "cameraPosition" : 1,
    "complexionTex" : 5,
    "eyebrowTex" : 5,
    "tattooTex" : 3,
    "actualTattooTex" : 0,
    "weights" : [
        0.4994338,
        5.712609,
        41.38589,
        29.52133,
        22.12362,
        0.7571349
    ],
    "browOffsetY" : -0.002350018,
    "browOffsetZ" : 0.0003289019,
    "noseBridgeScale" : 0.07412276,
    "noseTipScale" : -0.03616086,
    "chinScale" : -0.03254144,
    "cheekOffsetY" : -0.002399924,
    "eyeWidth" : -0.04655833,
    "jawWidth" : 0.05053351,
    "animation" : 0,
    "isCommander" : true,
    "skinToneId" : "Skin_00",
    "eyeColorId" : "Eye_00",
    "hairRootId" : "Hair_00",
    "hairTipId" : "Hair_00",
    "tattooColorId" : "Tattoo_06",
    "lipColorId" : "Lip_01",
    "customPortraitSaveVersion" : 0
}
