{
    "Description" : {
        "Id" : "guiTxrPort_backerMetke_utr",
        "Name" : "guiTxrPort_backerMetke_utr",
        "Details" : "Random",
        "Icon" : "guiTxrPort_backerMetke_utr"
    },
    "ID" : "guiTxrPort_backerMetke_utr",
    "backgroundColor" : {
        "r" : 0,
        "g" : 0,
        "b" : 0,
        "a" : 0
    },
    "headMesh" : 0.5,
    "hairMesh" : 2,
    "beardMesh" : 0,
    "suitMesh" : 0,
    "scar" : 3,
    "lightRig" : 5,
    "cameraPosition" : 4,
    "complexionTex" : 0,
    "eyebrowTex" : 2,
    "tattooTex" : 8,
    "actualTattooTex" : 0,
    "weights" : [
        36.16928,
        27.49708,
        1.425175,
        0.7983497,
        34.00246,
        0.1076564
    ],
    "browOffsetY" : -0.005134906,
    "browOffsetZ" : 0.00494854,
    "noseBridgeScale" : 0.1199983,
    "noseTipScale" : -0.2026633,
    "chinScale" : 0.161538,
    "cheekOffsetY" : 0.003500727,
    "eyeWidth" : 0.006626076,
    "jawWidth" : 0.01359378,
    "animation" : 0,
    "isCommander" : true,
    "skinToneId" : "Skin_06",
    "eyeColorId" : "Eye_05",
    "hairRootId" : "Hair_00",
    "hairTipId" : "Hair_00",
    "tattooColorId" : "Tattoo_02",
    "lipColorId" : "Lip_01",
    "customPortraitSaveVersion" : 0
}
