{
    "Description" : {
        "Id" : "guiTxrPort_backerBrown_utr",
        "Name" : "guiTxrPort_backerBrown_utr",
        "Details" : "Random",
        "Icon" : "guiTxrPort_backerBrown_utr"
    },
    "ID" : "guiTxrPort_backerBrown_utr",
    "backgroundColor" : {
        "r" : 0,
        "g" : 0,
        "b" : 0,
        "a" : 0
    },
    "headMesh" : 0.5,
    "hairMesh" : 16,
    "beardMesh" : 0,
    "suitMesh" : 2,
    "scar" : 0,
    "lightRig" : 3,
    "cameraPosition" : 0,
    "complexionTex" : 2,
    "eyebrowTex" : 4,
    "tattooTex" : 4,
    "actualTattooTex" : 0,
    "weights" : [
        72.63292,
        0.05427752,
        25.68861,
        0.7742966,
        0.833911,
        0.01598031
    ],
    "browOffsetY" : 0.002200042,
    "browOffsetZ" : -0.001496689,
    "noseBridgeScale" : 0.1512707,
    "noseTipScale" : -0.2615894,
    "chinScale" : 0.1057485,
    "cheekOffsetY" : -0.0008162433,
    "eyeWidth" : 0.03283659,
    "jawWidth" : 0.01311218,
    "animation" : 3,
    "isCommander" : true,
    "skinToneId" : "Skin_06",
    "eyeColorId" : "Eye_06",
    "hairRootId" : "Hair_12",
    "hairTipId" : "Hair_12",
    "tattooColorId" : "Tattoo_08",
    "lipColorId" : "Lip_01",
    "customPortraitSaveVersion" : 0
}
