{
    "Description" : {
        "Id" : "guiTxrPort_backerBozeman_utr",
        "Name" : "guiTxrPort_backerBozeman_utr",
        "Details" : "Random",
        "Icon" : "guiTxrPort_backerBozeman_utr"
    },
    "ID" : "guiTxrPort_backerBozeman_utr",
    "backgroundColor" : {
        "r" : 0,
        "g" : 0,
        "b" : 0,
        "a" : 0
    },
    "headMesh" : 0.5,
    "hairMesh" : 14,
    "beardMesh" : 0,
    "suitMesh" : 1,
    "scar" : 0,
    "lightRig" : 0,
    "cameraPosition" : 2,
    "complexionTex" : 3,
    "eyebrowTex" : 3,
    "tattooTex" : 6,
    "actualTattooTex" : 10,
    "weights" : [
        30.13886,
        23.93121,
        26.655,
        7.374458,
        10.43574,
        1.464746
    ],
    "browOffsetY" : 0.0005571197,
    "browOffsetZ" : 0.00613818,
    "noseBridgeScale" : 0.08062448,
    "noseTipScale" : -0.1942183,
    "chinScale" : 0.1692093,
    "cheekOffsetY" : -0.001372223,
    "eyeWidth" : -0.04334574,
    "jawWidth" : -0.02768537,
    "animation" : 0,
    "isCommander" : true,
    "skinToneId" : "Skin_06",
    "eyeColorId" : "Eye_07",
    "hairRootId" : "Hair_03",
    "hairTipId" : "Hair_03",
    "tattooColorId" : "Tattoo_02",
    "lipColorId" : "Lip_01",
    "customPortraitSaveVersion" : 0
}
