{
    "Description" : {
        "Id" : "guiTxrPort_backerChang_utr",
        "Name" : "guiTxrPort_backerChang_utr",
        "Details" : "Random",
        "Icon" : "guiTxrPort_backerChang_utr"
    },
    "ID" : "guiTxrPort_backerChang_utr",
    "backgroundColor" : {
        "r" : 0,
        "g" : 0,
        "b" : 0,
        "a" : 0
    },
    "headMesh" : 0.5,
    "hairMesh" : 4,
    "beardMesh" : 0,
    "suitMesh" : 2,
    "scar" : 0,
    "lightRig" : 1,
    "cameraPosition" : 0,
    "complexionTex" : 2,
    "eyebrowTex" : 1,
    "tattooTex" : 9,
    "actualTattooTex" : 10,
    "weights" : [
        38.92115,
        18.02143,
        0.03928392,
        35.38183,
        6.777553,
        0.8587536
    ],
    "browOffsetY" : -0.002610161,
    "browOffsetZ" : 0.003509395,
    "noseBridgeScale" : -0.1318033,
    "noseTipScale" : 0.1260684,
    "chinScale" : 0.02547905,
    "cheekOffsetY" : 0.003290303,
    "eyeWidth" : -0.04515823,
    "jawWidth" : 0.012877,
    "animation" : 3,
    "isCommander" : true,
    "skinToneId" : "Skin_04",
    "eyeColorId" : "Eye_02",
    "hairRootId" : "Hair_02",
    "hairTipId" : "Hair_02",
    "tattooColorId" : "Tattoo_10",
    "lipColorId" : "Lip_01",
    "customPortraitSaveVersion" : 0
}
