{
    "Description" : {
        "Id" : "guiTxrPort_backerBemis_utr",
        "Name" : "guiTxrPort_backerBemis_utr",
        "Details" : "Random",
        "Icon" : "guiTxrPort_backerBemis_utr"
    },
    "ID" : "guiTxrPort_backerBemis_utr",
    "backgroundColor" : {
        "r" : 0,
        "g" : 0,
        "b" : 0,
        "a" : 0
    },
    "headMesh" : 0.5,
    "hairMesh" : 8,
    "beardMesh" : 0,
    "suitMesh" : 1,
    "scar" : 3,
    "lightRig" : 5,
    "cameraPosition" : 1,
    "complexionTex" : 1,
    "eyebrowTex" : 4,
    "tattooTex" : 4,
    "actualTattooTex" : 12,
    "weights" : [
        43.59475,
        12.25656,
        28.00724,
        13.61473,
        0.3929347,
        2.133766
    ],
    "browOffsetY" : -0.001761547,
    "browOffsetZ" : 0.001000556,
    "noseBridgeScale" : -0.06687739,
    "noseTipScale" : -0.2284973,
    "chinScale" : 0.02319505,
    "cheekOffsetY" : -0.001770059,
    "eyeWidth" : -0.01013247,
    "jawWidth" : 0.002918494,
    "animation" : 4,
    "isCommander" : true,
    "skinToneId" : "Skin_06",
    "eyeColorId" : "Eye_05",
    "hairRootId" : "Hair_14",
    "hairTipId" : "Hair_14",
    "tattooColorId" : "Tattoo_08",
    "lipColorId" : "Lip_01",
    "customPortraitSaveVersion" : 0
}
