{
    "Description" : {
        "Id" : "guiTxrPort_Victoria_default_utr",
        "Name" : "guiTxrPort_Victoria_default_utr",
        "Details" : "Random",
        "Icon" : "guiTxrPort_Victoria_default_utr"
    },
    "ID" : "guiTxrPort_Victoria_default_utr",
    "backgroundColor" : {
        "r" : 0,
        "g" : 0,
        "b" : 0,
        "a" : 0
    },
    "headMesh" : 0.5,
    "hairMesh" : 6,
    "beardMesh" : 0,
    "suitMesh" : 0,
    "scar" : 12,
    "lightRig" : 4,
    "cameraPosition" : 4,
    "complexionTex" : 1,
    "eyebrowTex" : 4,
    "tattooTex" : 4,
    "actualTattooTex" : 4,
    "weights" : [
        13.36386,
        59.26216,
        26.01762,
        0.3403571,
        0.8054629,
        0.210545
    ],
    "browOffsetY" : 0.001553227,
    "browOffsetZ" : -0.001517439,
    "noseBridgeScale" : 0.03144381,
    "noseTipScale" : 0.2709659,
    "chinScale" : -0.1807883,
    "cheekOffsetY" : -0.003113634,
    "eyeWidth" : -0.02460301,
    "jawWidth" : 0.02423805,
    "animation" : 2,
    "isCommander" : true,
    "skinToneId" : "Skin_07",
    "eyeColorId" : "Eye_06",
    "hairRootId" : "Hair_02",
    "hairTipId" : "Hair_02",
    "tattooColorId" : "Tattoo_10",
    "lipColorId" : "Lip_01",
    "customPortraitSaveVersion" : 0
}
