{
    "Description" : {
        "Id" : "guiTxrPort_backerRyia_utr",
        "Name" : "guiTxrPort_backerRyia_utr",
        "Details" : "Random",
        "Icon" : "guiTxrPort_backerRyia_utr"
    },
    "ID" : "guiTxrPort_backerRyia_utr",
    "backgroundColor" : {
        "r" : 0,
        "g" : 0,
        "b" : 0,
        "a" : 0
    },
    "headMesh" : 0.5,
    "hairMesh" : 16,
    "beardMesh" : 0,
    "suitMesh" : 2,
    "scar" : 6,
    "lightRig" : 2,
    "cameraPosition" : 2,
    "complexionTex" : 5,
    "eyebrowTex" : 4,
    "tattooTex" : 4,
    "actualTattooTex" : 0,
    "weights" : [
        52.48582,
        12.70109,
        0.77975,
        11.89909,
        1.19466,
        20.93961
    ],
    "browOffsetY" : 0.006659484,
    "browOffsetZ" : -0.003943435,
    "noseBridgeScale" : 0.1907025,
    "noseTipScale" : 0.1286505,
    "chinScale" : -0.06544383,
    "cheekOffsetY" : 0.0005473655,
    "eyeWidth" : -0.001529843,
    "jawWidth" : 0.01108128,
    "animation" : 1,
    "isCommander" : true,
    "skinToneId" : "Skin_06",
    "eyeColorId" : "Eye_03",
    "hairRootId" : "Hair_03",
    "hairTipId" : "Hair_03",
    "tattooColorId" : "Tattoo_06",
    "lipColorId" : "Lip_01",
    "customPortraitSaveVersion" : 0
}
