{
    "Description" : {
        "Id" : "guiTxrPort_SE03_PirateLeader_def_utr",
        "Name" : "guiTxrPort_SE03_PirateLeader_def_utr",
        "Details" : "Random",
        "Icon" : "guiTxrPort_SE03_PirateLeader_def_utr"
    },
    "ID" : "guiTxrPort_SE03_PirateLeader_def_utr",
    "backgroundColor" : {
        "r" : 0,
        "g" : 0,
        "b" : 0,
        "a" : 0
    },
    "headMesh" : 0.5,
    "hairMesh" : 1,
    "beardMesh" : 0,
    "suitMesh" : 1,
    "scar" : 13,
    "lightRig" : 2,
    "cameraPosition" : 0,
    "complexionTex" : 5,
    "eyebrowTex" : 2,
    "tattooTex" : 2,
    "actualTattooTex" : 1,
    "weights" : [
        14.596,
        47.28794,
        26.96511,
        4.83266,
        4.222299,
        2.095999
    ],
    "browOffsetY" : -0.004418207,
    "browOffsetZ" : -0.006579965,
    "noseBridgeScale" : -0.0009093523,
    "noseTipScale" : 0.03577606,
    "chinScale" : 0.0875616,
    "cheekOffsetY" : -0.002217703,
    "eyeWidth" : -0.02995749,
    "jawWidth" : -0.06480303,
    "animation" : 3,
    "isCommander" : true,
    "skinToneId" : "Skin_05",
    "eyeColorId" : "Eye_00",
    "hairRootId" : "Hair_01",
    "hairTipId" : "Hair_01",
    "tattooColorId" : "Tattoo_10",
    "lipColorId" : "Lip_01",
    "customPortraitSaveVersion" : 0
}
