{
    "Description" : {
        "Id" : "ladywithhood",
        "Name" : "ladywithhood",
        "Details" : "Random",
        "Icon" : "ladywithhood"
    },
    "ID" : "ladywithhood",
    "backgroundColor" : {
        "r" : 0,
        "g" : 0,
        "b" : 0,
        "a" : 0
    },
    "headMesh" : 0.5,
    "hairMesh" : 12,
    "beardMesh" : 0,
    "suitMesh" : 0,
    "scar" : 0,
    "lightRig" : 1,
    "cameraPosition" : 2,
    "complexionTex" : 3,
    "eyebrowTex" : 1,
    "tattooTex" : 7,
    "actualTattooTex" : 10,
    "weights" : [
        6.727865,
        23.44346,
        6.765537,
        58.19475,
        3.955548,
        0.9128446
    ],
    "browOffsetY" : -0.005145719,
    "browOffsetZ" : 0.004083874,
    "noseBridgeScale" : 0.07276931,
    "noseTipScale" : -0.2416896,
    "chinScale" : -0.1824341,
    "cheekOffsetY" : 0.002135308,
    "eyeWidth" : 0.0434019,
    "jawWidth" : -0.09630086,
    "animation" : 0,
    "isCommander" : true,
    "skinToneId" : "Skin_01",
    "eyeColorId" : "Eye_01",
    "hairRootId" : "Hair_12",
    "hairTipId" : "Hair_12",
    "tattooColorId" : "Tattoo_02",
    "lipColorId" : "Lip_01",
    "customPortraitSaveVersion" : 0
}
