{
    "Description" : {
        "Id" : "Npc_humanfemale_glory_cr",
        "Name" : "Npc_humanfemale_glory_cr",
        "Details" : "Random",
        "Icon" : "Npc_humanfemale_glory_cr"
    },
    "ID" : "Npc_humanfemale_glory_cr",
    "backgroundColor" : {
        "r" : 0,
        "g" : 0,
        "b" : 0,
        "a" : 0
    },
    "headMesh" : 0.5,
    "hairMesh" : 6,
    "beardMesh" : 0,
    "suitMesh" : 0,
    "scar" : 1,
    "lightRig" : 3,
    "cameraPosition" : 4,
    "complexionTex" : 2,
    "eyebrowTex" : 5,
    "tattooTex" : 11,
    "actualTattooTex" : 0,
    "weights" : [
        49.19442,
        5.004778,
        6.998398,
        6.209257,
        30.3094,
        2.283752
    ],
    "browOffsetY" : -0.0008829099,
    "browOffsetZ" : -0.006826533,
    "noseBridgeScale" : -0.06777237,
    "noseTipScale" : 0.02264775,
    "chinScale" : -0.1218521,
    "cheekOffsetY" : -0.001896332,
    "eyeWidth" : 0.0386398,
    "jawWidth" : 0.03697243,
    "animation" : 0,
    "isCommander" : true,
    "skinToneId" : "Skin_04",
    "eyeColorId" : "Eye_02",
    "hairRootId" : "Hair_17",
    "hairTipId" : "Hair_17",
    "tattooColorId" : "Tattoo_06",
    "lipColorId" : "Lip_01",
    "customPortraitSaveVersion" : 0
}
