{
    "Description" : {
        "Id" : "pilot_at_max_p",
        "Name" : "pilot_at_max_p",
        "Details" : "Random",
        "Icon" : "pilot_at_max_p"
    },
    "ID" : "pilot_at_max_p",
    "backgroundColor" : {
        "r" : 0,
        "g" : 0,
        "b" : 0,
        "a" : 0
    },
    "headMesh" : 0.5,
    "hairMesh" : 1,
    "beardMesh" : 0,
    "suitMesh" : 2,
    "scar" : 0,
    "lightRig" : 2,
    "cameraPosition" : 3,
    "complexionTex" : 5,
    "eyebrowTex" : 5,
    "tattooTex" : 2,
    "actualTattooTex" : 0,
    "weights" : [
        29.82763,
        3.924363,
        37.96994,
        7.143021,
        9.620946,
        11.51409
    ],
    "browOffsetY" : 0.0005522965,
    "browOffsetZ" : -0.003488759,
    "noseBridgeScale" : 0.1484585,
    "noseTipScale" : 0.2930984,
    "chinScale" : -0.1166306,
    "cheekOffsetY" : -0.00241103,
    "eyeWidth" : -0.04914776,
    "jawWidth" : 0.01157855,
    "animation" : 0,
    "isCommander" : true,
    "skinToneId" : "Skin_00",
    "eyeColorId" : "Eye_06",
    "hairRootId" : "Hair_12",
    "hairTipId" : "Hair_12",
    "tattooColorId" : "Tattoo_02",
    "lipColorId" : "Lip_01",
    "customPortraitSaveVersion" : 0
}
