{
    "Description" : {
        "Id" : "pilot_at_geezer_p",
        "Name" : "pilot_at_geezer_p",
        "Details" : "Random",
        "Icon" : "pilot_at_geezer_p"
    },
    "ID" : "pilot_at_geezer_p",
    "backgroundColor" : {
        "r" : 0,
        "g" : 0,
        "b" : 0,
        "a" : 0
    },
    "headMesh" : 0.5,
    "hairMesh" : 5,
    "beardMesh" : 0,
    "suitMesh" : 1,
    "scar" : 2,
    "lightRig" : 3,
    "cameraPosition" : 1,
    "complexionTex" : 2,
    "eyebrowTex" : 4,
    "tattooTex" : 2,
    "actualTattooTex" : 6,
    "weights" : [
        22.83867,
        59.15997,
        13.53709,
        1.815288,
        0.9085838,
        1.740411
    ],
    "browOffsetY" : 0.001165027,
    "browOffsetZ" : 0.001908064,
    "noseBridgeScale" : 0.03355563,
    "noseTipScale" : 0.1229064,
    "chinScale" : 0.1026481,
    "cheekOffsetY" : -0.003448055,
    "eyeWidth" : -0.02823731,
    "jawWidth" : 0.002932084,
    "animation" : 1,
    "isCommander" : true,
    "skinToneId" : "Skin_07",
    "eyeColorId" : "Eye_03",
    "hairRootId" : "Hair_11",
    "hairTipId" : "Hair_11",
    "tattooColorId" : "Tattoo_10",
    "lipColorId" : "Lip_01",
    "customPortraitSaveVersion" : 0
}
