{
    "Description" : {
        "Id" : "Takeshi",
        "Name" : "Takeshi",
        "Details" : "Random",
        "Icon" : "Takeshi"
    },
    "ID" : "Takeshi",
    "backgroundColor" : {
        "r" : 0,
        "g" : 0,
        "b" : 0,
        "a" : 0
    },
    "headMesh" : 0.5,
    "hairMesh" : 2,
    "beardMesh" : 0,
    "suitMesh" : 0,
    "scar" : 0,
    "lightRig" : 0,
    "cameraPosition" : 1,
    "complexionTex" : 5,
    "eyebrowTex" : 4,
    "tattooTex" : 4,
    "actualTattooTex" : 0,
    "weights" : [
        37.58998,
        9.618345,
        22.43133,
        25.05867,
        4.526548,
        0.7751191
    ],
    "browOffsetY" : -0.005362631,
    "browOffsetZ" : 0.004237589,
    "noseBridgeScale" : 0.06517892,
    "noseTipScale" : 0.233812,
    "chinScale" : -0.06624492,
    "cheekOffsetY" : -0.00043284,
    "eyeWidth" : 0.010212,
    "jawWidth" : 0.0858371,
    "animation" : 0,
    "isCommander" : true,
    "skinToneId" : "Skin_04",
    "eyeColorId" : "Eye_01",
    "hairRootId" : "Hair_13",
    "hairTipId" : "Hair_13",
    "tattooColorId" : "Tattoo_04",
    "lipColorId" : "Lip_01",
    "customPortraitSaveVersion" : 0
}
