{
    "Description" : {
        "Id" : "pilot_at_plato_p",
        "Name" : "pilot_at_plato_p",
        "Details" : "Random",
        "Icon" : "pilot_at_plato_p"
    },
    "ID" : "pilot_at_plato_p",
    "backgroundColor" : {
        "r" : 0,
        "g" : 0,
        "b" : 0,
        "a" : 0
    },
    "headMesh" : 0.5,
    "hairMesh" : 17,
    "beardMesh" : 0,
    "suitMesh" : 1,
    "scar" : 7,
    "lightRig" : 2,
    "cameraPosition" : 3,
    "complexionTex" : 2,
    "eyebrowTex" : 5,
    "tattooTex" : 6,
    "actualTattooTex" : 0,
    "weights" : [
        76.76886,
        22.21451,
        0.5901612,
        0.3110791,
        0.1009618,
        0.01444311
    ],
    "browOffsetY" : -0.006700102,
    "browOffsetZ" : 0.0008350834,
    "noseBridgeScale" : -0.1740439,
    "noseTipScale" : 0.1223413,
    "chinScale" : 0.1551262,
    "cheekOffsetY" : 0.0003345221,
    "eyeWidth" : 0.03003564,
    "jawWidth" : 0.07856121,
    "animation" : 1,
    "isCommander" : true,
    "skinToneId" : "Skin_04",
    "eyeColorId" : "Eye_00",
    "hairRootId" : "Hair_02",
    "hairTipId" : "Hair_02",
    "tattooColorId" : "Tattoo_01",
    "lipColorId" : "Lip_01",
    "customPortraitSaveVersion" : 0
}
