{
    "Description" : {
        "Id" : "Tanker_02",
        "Name" : "Tanker_02",
        "Details" : "Random",
        "Icon" : "Tanker_02"
    },
    "ID" : "Tanker_02",
    "backgroundColor" : {
        "r" : 0,
        "g" : 0,
        "b" : 0,
        "a" : 0
    },
    "headMesh" : 0.5,
    "hairMesh" : 4,
    "beardMesh" : 0,
    "suitMesh" : 2,
    "scar" : 0,
    "lightRig" : 0,
    "cameraPosition" : 3,
    "complexionTex" : 1,
    "eyebrowTex" : 1,
    "tattooTex" : 0,
    "actualTattooTex" : 0,
    "weights" : [
        57.97271,
        5.558534,
        1.572589,
        0.147897,
        0.5597574,
        34.18851
    ],
    "browOffsetY" : -0.001601099,
    "browOffsetZ" : -0.003364711,
    "noseBridgeScale" : 0.1101733,
    "noseTipScale" : -0.2938202,
    "chinScale" : 0.03674166,
    "cheekOffsetY" : 0.001016576,
    "eyeWidth" : -0.03278772,
    "jawWidth" : 0.04507246,
    "animation" : 4,
    "isCommander" : true,
    "skinToneId" : "Skin_06",
    "eyeColorId" : "Eye_06",
    "hairRootId" : "Hair_03",
    "hairTipId" : "Hair_03",
    "tattooColorId" : "Tattoo_09",
    "lipColorId" : "Lip_01",
    "customPortraitSaveVersion" : 0
}
