{
    "Description" : {
        "Id" : "bear",
        "Name" : "bear",
        "Details" : "Random",
        "Icon" : "bear"
    },
    "ID" : "bear",
    "backgroundColor" : {
        "r" : 0,
        "g" : 0,
        "b" : 0,
        "a" : 0
    },
    "headMesh" : 0.5,
    "hairMesh" : 15,
    "beardMesh" : 0,
    "suitMesh" : 2,
    "scar" : 10,
    "lightRig" : 2,
    "cameraPosition" : 0,
    "complexionTex" : 0,
    "eyebrowTex" : 3,
    "tattooTex" : 9,
    "actualTattooTex" : 0,
    "weights" : [
        43.8975,
        4.283751,
        15.7034,
        4.3168,
        31.49747,
        0.3010821
    ],
    "browOffsetY" : 0.006316679,
    "browOffsetZ" : -0.005749434,
    "noseBridgeScale" : 0.1216276,
    "noseTipScale" : 0.2573833,
    "chinScale" : 0.01828864,
    "cheekOffsetY" : -0.0007027453,
    "eyeWidth" : 0.04460067,
    "jawWidth" : 0.01668113,
    "animation" : 0,
    "isCommander" : true,
    "skinToneId" : "Skin_04",
    "eyeColorId" : "Eye_02",
    "hairRootId" : "Hair_03",
    "hairTipId" : "Hair_03",
    "tattooColorId" : "Tattoo_01",
    "lipColorId" : "Lip_01",
    "customPortraitSaveVersion" : 0
}
