{
    "Description" : {
        "Id" : "guiTxrPort_backerNick_utr",
        "Name" : "guiTxrPort_backerNick_utr",
        "Details" : "Random",
        "Icon" : "guiTxrPort_backerNick_utr"
    },
    "ID" : "guiTxrPort_backerNick_utr",
    "backgroundColor" : {
        "r" : 0,
        "g" : 0,
        "b" : 0,
        "a" : 0
    },
    "headMesh" : 0.5,
    "hairMesh" : 0,
    "beardMesh" : 0,
    "suitMesh" : 1,
    "scar" : 7,
    "lightRig" : 4,
    "cameraPosition" : 1,
    "complexionTex" : 2,
    "eyebrowTex" : 3,
    "tattooTex" : 6,
    "actualTattooTex" : 0,
    "weights" : [
        50.93136,
        0.3415107,
        25.90954,
        10.81061,
        10.4494,
        1.557577
    ],
    "browOffsetY" : -0.006920259,
    "browOffsetZ" : -0.0007816776,
    "noseBridgeScale" : -0.1413615,
    "noseTipScale" : 0.0234934,
    "chinScale" : -0.1429201,
    "cheekOffsetY" : -0.001717026,
    "eyeWidth" : 0.03712279,
    "jawWidth" : -0.04268359,
    "animation" : 1,
    "isCommander" : true,
    "skinToneId" : "Skin_06",
    "eyeColorId" : "Eye_03",
    "hairRootId" : "Hair_02",
    "hairTipId" : "Hair_02",
    "tattooColorId" : "Tattoo_02",
    "lipColorId" : "Lip_01",
    "customPortraitSaveVersion" : 0
}
