{
    "Description" : {
        "Id" : "guiTxrPort_SE04_PrisonWarden_def_utr",
        "Name" : "guiTxrPort_SE04_PrisonWarden_def_utr",
        "Details" : "Random",
        "Icon" : "guiTxrPort_SE04_PrisonWarden_def_utr"
    },
    "ID" : "guiTxrPort_SE04_PrisonWarden_def_utr",
    "backgroundColor" : {
        "r" : 0,
        "g" : 0,
        "b" : 0,
        "a" : 0
    },
    "headMesh" : 0.5,
    "hairMesh" : 16,
    "beardMesh" : 0,
    "suitMesh" : 2,
    "scar" : 0,
    "lightRig" : 5,
    "cameraPosition" : 1,
    "complexionTex" : 4,
    "eyebrowTex" : 0,
    "tattooTex" : 9,
    "actualTattooTex" : 14,
    "weights" : [
        25.41907,
        30.97403,
        10.84433,
        4.222379,
        25.86924,
        2.670961
    ],
    "browOffsetY" : 0.005856175,
    "browOffsetZ" : 0.00499689,
    "noseBridgeScale" : -0.08736446,
    "noseTipScale" : -0.0158147,
    "chinScale" : -0.1160222,
    "cheekOffsetY" : 0.0025706,
    "eyeWidth" : -0.04857334,
    "jawWidth" : 0.06746648,
    "animation" : 3,
    "isCommander" : true,
    "skinToneId" : "Skin_07",
    "eyeColorId" : "Eye_06",
    "hairRootId" : "Hair_12",
    "hairTipId" : "Hair_12",
    "tattooColorId" : "Tattoo_07",
    "lipColorId" : "Lip_01",
    "customPortraitSaveVersion" : 0
}
