{
    "Description" : {
        "Id" : "guiTxrPort_backerSwansonA_utr",
        "Name" : "guiTxrPort_backerSwansonA_utr",
        "Details" : "Random",
        "Icon" : "guiTxrPort_backerSwansonA_utr"
    },
    "ID" : "guiTxrPort_backerSwansonA_utr",
    "backgroundColor" : {
        "r" : 0,
        "g" : 0,
        "b" : 0,
        "a" : 0
    },
    "headMesh" : 0.5,
    "hairMesh" : 7,
    "beardMesh" : 0,
    "suitMesh" : 0,
    "scar" : 9,
    "lightRig" : 2,
    "cameraPosition" : 2,
    "complexionTex" : 0,
    "eyebrowTex" : 3,
    "tattooTex" : 11,
    "actualTattooTex" : 13,
    "weights" : [
        35.70438,
        11.70762,
        31.98891,
        19.06125,
        1.059558,
        0.4782821
    ],
    "browOffsetY" : -0.005874025,
    "browOffsetZ" : -0.0009904157,
    "noseBridgeScale" : -0.09030788,
    "noseTipScale" : 0.03232688,
    "chinScale" : -0.1406138,
    "cheekOffsetY" : -0.003774887,
    "eyeWidth" : -0.02062809,
    "jawWidth" : -0.09797492,
    "animation" : 2,
    "isCommander" : true,
    "skinToneId" : "Skin_06",
    "eyeColorId" : "Eye_00",
    "hairRootId" : "Hair_09",
    "hairTipId" : "Hair_09",
    "tattooColorId" : "Tattoo_06",
    "lipColorId" : "Lip_01",
    "customPortraitSaveVersion" : 0
}
