{
    "Description" : {
        "Id" : "guiTxrPort_backerSwansonA_utr",
        "Name" : "guiTxrPort_backerSwansonA_utr",
        "Details" : "Random",
        "Icon" : "guiTxrPort_backerSwansonA_utr"
    },
    "ID" : "guiTxrPort_backerSwansonA_utr",
    "backgroundColor" : {
        "r" : 0,
        "g" : 0,
        "b" : 0,
        "a" : 0
    },
    "headMesh" : 0.5,
    "hairMesh" : 9,
    "beardMesh" : 0,
    "suitMesh" : 2,
    "scar" : 14,
    "lightRig" : 0,
    "cameraPosition" : 2,
    "complexionTex" : 2,
    "eyebrowTex" : 2,
    "tattooTex" : 7,
    "actualTattooTex" : 0,
    "weights" : [
        41.05537,
        16.62127,
        3.87762,
        32.71923,
        4.137184,
        1.589332
    ],
    "browOffsetY" : 0.006229986,
    "browOffsetZ" : -0.005497287,
    "noseBridgeScale" : 0.1699087,
    "noseTipScale" : -0.1769661,
    "chinScale" : -0.07855704,
    "cheekOffsetY" : 0.0006383806,
    "eyeWidth" : -0.04479052,
    "jawWidth" : -0.02859534,
    "animation" : 3,
    "isCommander" : true,
    "skinToneId" : "Skin_04",
    "eyeColorId" : "Eye_02",
    "hairRootId" : "Hair_13",
    "hairTipId" : "Hair_13",
    "tattooColorId" : "Tattoo_02",
    "lipColorId" : "Lip_01",
    "customPortraitSaveVersion" : 0
}
