{
    "Description" : {
        "Id" : "guiTxrPort_backerDurand_utr",
        "Name" : "guiTxrPort_backerDurand_utr",
        "Details" : "Random",
        "Icon" : "guiTxrPort_backerDurand_utr"
    },
    "ID" : "guiTxrPort_backerDurand_utr",
    "backgroundColor" : {
        "r" : 0,
        "g" : 0,
        "b" : 0,
        "a" : 0
    },
    "headMesh" : 0.5,
    "hairMesh" : 17,
    "beardMesh" : 0,
    "suitMesh" : 2,
    "scar" : 5,
    "lightRig" : 4,
    "cameraPosition" : 1,
    "complexionTex" : 2,
    "eyebrowTex" : 5,
    "tattooTex" : 2,
    "actualTattooTex" : 0,
    "weights" : [
        70.8808,
        1.792016,
        26.12267,
        1.119713,
        0.06294129,
        0.02186507
    ],
    "browOffsetY" : -0.003408927,
    "browOffsetZ" : 0.003197473,
    "noseBridgeScale" : -0.0179301,
    "noseTipScale" : -0.2137398,
    "chinScale" : -0.1424124,
    "cheekOffsetY" : -0.004764734,
    "eyeWidth" : -0.0061086,
    "jawWidth" : -0.024445,
    "animation" : 2,
    "isCommander" : true,
    "skinToneId" : "Skin_06",
    "eyeColorId" : "Eye_03",
    "hairRootId" : "Hair_04",
    "hairTipId" : "Hair_04",
    "tattooColorId" : "Tattoo_06",
    "lipColorId" : "Lip_01",
    "customPortraitSaveVersion" : 0
}
