{
    "Description" : {
        "Id" : "guiTxrPort_Shepard3_utr",
        "Name" : "guiTxrPort_Shepard3_utr",
        "Details" : "Random",
        "Icon" : "guiTxrPort_Shepard3_utr"
    },
    "ID" : "guiTxrPort_Shepard3_utr",
    "backgroundColor" : {
        "r" : 0,
        "g" : 0,
        "b" : 0,
        "a" : 0
    },
    "headMesh" : 0.5,
    "hairMesh" : 15,
    "beardMesh" : 0,
    "suitMesh" : 0,
    "scar" : 9,
    "lightRig" : 3,
    "cameraPosition" : 4,
    "complexionTex" : 5,
    "eyebrowTex" : 3,
    "tattooTex" : 9,
    "actualTattooTex" : 13,
    "weights" : [
        60.04264,
        25.01051,
        8.863594,
        1.325674,
        3.403322,
        1.354263
    ],
    "browOffsetY" : 0.003365926,
    "browOffsetZ" : 0.001460849,
    "noseBridgeScale" : 0.08242068,
    "noseTipScale" : -0.1193109,
    "chinScale" : -0.04315045,
    "cheekOffsetY" : 0.004464626,
    "eyeWidth" : 0.01987265,
    "jawWidth" : 0.01389939,
    "animation" : 3,
    "isCommander" : true,
    "skinToneId" : "Skin_06",
    "eyeColorId" : "Eye_06",
    "hairRootId" : "Hair_17",
    "hairTipId" : "Hair_17",
    "tattooColorId" : "Tattoo_09",
    "lipColorId" : "Lip_01",
    "customPortraitSaveVersion" : 0
}
