{
    "Description" : {
        "Id" : "guiTxrPort_jkHBFT_utr",
        "Name" : "guiTxrPort_jkHBFT_utr",
        "Details" : "Random",
        "Icon" : "guiTxrPort_jkHBFT_utr"
    },
    "ID" : "guiTxrPort_jkHBFT_utr",
    "backgroundColor" : {
        "r" : 0,
        "g" : 0,
        "b" : 0,
        "a" : 0
    },
    "headMesh" : 0.5,
    "hairMesh" : 14,
    "beardMesh" : 0,
    "suitMesh" : 0,
    "scar" : 5,
    "lightRig" : 2,
    "cameraPosition" : 2,
    "complexionTex" : 0,
    "eyebrowTex" : 3,
    "tattooTex" : 9,
    "actualTattooTex" : 10,
    "weights" : [
        65.29113,
        4.370559,
        0.06006811,
        0.01043492,
        0.00423064,
        30.26357
    ],
    "browOffsetY" : -0.005707941,
    "browOffsetZ" : 0.003983661,
    "noseBridgeScale" : -0.1030512,
    "noseTipScale" : 0.1626005,
    "chinScale" : -0.100945,
    "cheekOffsetY" : -0.002491351,
    "eyeWidth" : -0.02635272,
    "jawWidth" : 0.06272385,
    "animation" : 3,
    "isCommander" : true,
    "skinToneId" : "Skin_04",
    "eyeColorId" : "Eye_07",
    "hairRootId" : "Hair_00",
    "hairTipId" : "Hair_00",
    "tattooColorId" : "Tattoo_06",
    "lipColorId" : "Lip_01",
    "customPortraitSaveVersion" : 0
}
