{
    "Description" : {
        "Id" : "guiTxrPort_jkBloodyDoves_utr",
        "Name" : "guiTxrPort_jkBloodyDoves_utr",
        "Details" : "Random",
        "Icon" : "guiTxrPort_jkBloodyDoves_utr"
    },
    "ID" : "guiTxrPort_jkBloodyDoves_utr",
    "backgroundColor" : {
        "r" : 0,
        "g" : 0,
        "b" : 0,
        "a" : 0
    },
    "headMesh" : 0.5,
    "hairMesh" : 4,
    "beardMesh" : 0,
    "suitMesh" : 0,
    "scar" : 0,
    "lightRig" : 3,
    "cameraPosition" : 1,
    "complexionTex" : 4,
    "eyebrowTex" : 3,
    "tattooTex" : 2,
    "actualTattooTex" : 1,
    "weights" : [
        59.52768,
        22.46701,
        7.887546,
        3.850073,
        3.846601,
        2.421088
    ],
    "browOffsetY" : -0.001340242,
    "browOffsetZ" : 0.004442542,
    "noseBridgeScale" : 0.01007268,
    "noseTipScale" : 0.09552541,
    "chinScale" : 0.1892547,
    "cheekOffsetY" : -0.004277796,
    "eyeWidth" : -0.01081842,
    "jawWidth" : -0.0599077,
    "animation" : 0,
    "isCommander" : true,
    "skinToneId" : "Skin_06",
    "eyeColorId" : "Eye_03",
    "hairRootId" : "Hair_02",
    "hairTipId" : "Hair_02",
    "tattooColorId" : "Tattoo_08",
    "lipColorId" : "Lip_01",
    "customPortraitSaveVersion" : 0
}
