{
    "Description" : {
        "Id" : "valkyrate",
        "Name" : "valkyrate",
        "Details" : "Random",
        "Icon" : "valkyrate"
    },
    "ID" : "valkyrate",
    "backgroundColor" : {
        "r" : 0,
        "g" : 0,
        "b" : 0,
        "a" : 0
    },
    "headMesh" : 0.5,
    "hairMesh" : 14,
    "beardMesh" : 0,
    "suitMesh" : 0,
    "scar" : 4,
    "lightRig" : 5,
    "cameraPosition" : 0,
    "complexionTex" : 4,
    "eyebrowTex" : 0,
    "tattooTex" : 4,
    "actualTattooTex" : 0,
    "weights" : [
        21.77612,
        59.00422,
        9.965557,
        8.8027,
        0.3849024,
        0.06651611
    ],
    "browOffsetY" : 0.002878664,
    "browOffsetZ" : -0.0008010389,
    "noseBridgeScale" : -0.0671685,
    "noseTipScale" : -0.121883,
    "chinScale" : -0.1912546,
    "cheekOffsetY" : -0.002987486,
    "eyeWidth" : 0.01645242,
    "jawWidth" : -0.07706103,
    "animation" : 2,
    "isCommander" : true,
    "skinToneId" : "Skin_05",
    "eyeColorId" : "Eye_04",
    "hairRootId" : "Hair_12",
    "hairTipId" : "Hair_12",
    "tattooColorId" : "Tattoo_02",
    "lipColorId" : "Lip_01",
    "customPortraitSaveVersion" : 0
}
