{
    "Description" : {
        "Id" : "clanner_orange_blue",
        "Name" : "clanner_orange_blue",
        "Details" : "Random",
        "Icon" : "clanner_orange_blue"
    },
    "ID" : "clanner_orange_blue",
    "backgroundColor" : {
        "r" : 0,
        "g" : 0,
        "b" : 0,
        "a" : 0
    },
    "headMesh" : 0.5,
    "hairMesh" : 13,
    "beardMesh" : 0,
    "suitMesh" : 0,
    "scar" : 13,
    "lightRig" : 0,
    "cameraPosition" : 2,
    "complexionTex" : 3,
    "eyebrowTex" : 4,
    "tattooTex" : 10,
    "actualTattooTex" : 0,
    "weights" : [
        24.44792,
        14.0147,
        30.80179,
        9.150193,
        0.2984946,
        21.2869
    ],
    "browOffsetY" : -0.001235995,
    "browOffsetZ" : 0.001025642,
    "noseBridgeScale" : 0.0836915,
    "noseTipScale" : -0.167348,
    "chinScale" : 0.06189298,
    "cheekOffsetY" : -0.004706251,
    "eyeWidth" : -0.04679441,
    "jawWidth" : -0.02304913,
    "animation" : 1,
    "isCommander" : true,
    "skinToneId" : "Skin_00",
    "eyeColorId" : "Eye_04",
    "hairRootId" : "Hair_02",
    "hairTipId" : "Hair_02",
    "tattooColorId" : "Tattoo_03",
    "lipColorId" : "Lip_01",
    "customPortraitSaveVersion" : 0
}
