{
    "Description" : {
        "Id" : "gasmasky",
        "Name" : "gasmasky",
        "Details" : "Random",
        "Icon" : "gasmasky"
    },
    "ID" : "gasmasky",
    "backgroundColor" : {
        "r" : 0,
        "g" : 0,
        "b" : 0,
        "a" : 0
    },
    "headMesh" : 0.5,
    "hairMesh" : 17,
    "beardMesh" : 0,
    "suitMesh" : 1,
    "scar" : 0,
    "lightRig" : 0,
    "cameraPosition" : 4,
    "complexionTex" : 0,
    "eyebrowTex" : 1,
    "tattooTex" : 9,
    "actualTattooTex" : 0,
    "weights" : [
        26.95631,
        6.707255,
        7.038846,
        27.22731,
        29.30462,
        2.765651
    ],
    "browOffsetY" : 0.001246927,
    "browOffsetZ" : -0.000491207,
    "noseBridgeScale" : 0.1643069,
    "noseTipScale" : -0.1462055,
    "chinScale" : 0.03588727,
    "cheekOffsetY" : -0.004482444,
    "eyeWidth" : 0.01868977,
    "jawWidth" : 0.05030394,
    "animation" : 0,
    "isCommander" : true,
    "skinToneId" : "Skin_03",
    "eyeColorId" : "Eye_06",
    "hairRootId" : "Hair_17",
    "hairTipId" : "Hair_17",
    "tattooColorId" : "Tattoo_02",
    "lipColorId" : "Lip_01",
    "customPortraitSaveVersion" : 0
}
