{
    "Description" : {
        "Id" : "guiTxrPort_Morphyum_utr",
        "Name" : "guiTxrPort_Morphyum_utr",
        "Details" : "Random",
        "Icon" : "guiTxrPort_Morphyum_utr"
    },
    "ID" : "guiTxrPort_Morphyum_utr",
    "backgroundColor" : {
        "r" : 0,
        "g" : 0,
        "b" : 0,
        "a" : 0
    },
    "headMesh" : 0.5,
    "hairMesh" : 6,
    "beardMesh" : 0,
    "suitMesh" : 0,
    "scar" : 7,
    "lightRig" : 2,
    "cameraPosition" : 4,
    "complexionTex" : 4,
    "eyebrowTex" : 0,
    "tattooTex" : 6,
    "actualTattooTex" : 0,
    "weights" : [
        38.80624,
        31.20494,
        0.05967204,
        1.104233,
        28.80621,
        0.01870435
    ],
    "browOffsetY" : 0.006613943,
    "browOffsetZ" : -0.003378813,
    "noseBridgeScale" : 0.1120931,
    "noseTipScale" : -0.05721613,
    "chinScale" : -0.0117625,
    "cheekOffsetY" : 0.001171146,
    "eyeWidth" : 0.02849759,
    "jawWidth" : -0.06931663,
    "animation" : 0,
    "isCommander" : true,
    "skinToneId" : "Skin_04",
    "eyeColorId" : "Eye_04",
    "hairRootId" : "Hair_03",
    "hairTipId" : "Hair_03",
    "tattooColorId" : "Tattoo_05",
    "lipColorId" : "Lip_01",
    "customPortraitSaveVersion" : 0
}
