{
    "Description" : {
        "Id" : "guiTxrPort_Aaeris_utr",
        "Name" : "guiTxrPort_Aaeris_utr",
        "Details" : "Random",
        "Icon" : "guiTxrPort_Aaeris_utr"
    },
    "ID" : "guiTxrPort_Aaeris_utr",
    "backgroundColor" : {
        "r" : 0,
        "g" : 0,
        "b" : 0,
        "a" : 0
    },
    "headMesh" : 0.5,
    "hairMesh" : 17,
    "beardMesh" : 0,
    "suitMesh" : 0,
    "scar" : 6,
    "lightRig" : 2,
    "cameraPosition" : 0,
    "complexionTex" : 4,
    "eyebrowTex" : 3,
    "tattooTex" : 2,
    "actualTattooTex" : 0,
    "weights" : [
        32.25895,
        27.51847,
        10.25189,
        15.14353,
        14.76205,
        0.06510945
    ],
    "browOffsetY" : -0.0009698378,
    "browOffsetZ" : 0.005907357,
    "noseBridgeScale" : 0.1820762,
    "noseTipScale" : 0.1233814,
    "chinScale" : 0.143463,
    "cheekOffsetY" : -0.004441698,
    "eyeWidth" : -0.004718548,
    "jawWidth" : -0.05893009,
    "animation" : 1,
    "isCommander" : true,
    "skinToneId" : "Skin_04",
    "eyeColorId" : "Eye_03",
    "hairRootId" : "Hair_09",
    "hairTipId" : "Hair_09",
    "tattooColorId" : "Tattoo_05",
    "lipColorId" : "Lip_01",
    "customPortraitSaveVersion" : 0
}
