{
    "Description" : {
        "Id" : "guiTxrPort_Kharak_utr",
        "Name" : "guiTxrPort_Kharak_utr",
        "Details" : "Random",
        "Icon" : "guiTxrPort_Kharak_utr"
    },
    "ID" : "guiTxrPort_Kharak_utr",
    "backgroundColor" : {
        "r" : 0,
        "g" : 0,
        "b" : 0,
        "a" : 0
    },
    "headMesh" : 0.5,
    "hairMesh" : 0,
    "beardMesh" : 0,
    "suitMesh" : 1,
    "scar" : 0,
    "lightRig" : 5,
    "cameraPosition" : 2,
    "complexionTex" : 5,
    "eyebrowTex" : 5,
    "tattooTex" : 9,
    "actualTattooTex" : 0,
    "weights" : [
        20.50515,
        18.6293,
        18.8447,
        26.93036,
        11.84342,
        3.247059
    ],
    "browOffsetY" : -0.002013413,
    "browOffsetZ" : -0.004349242,
    "noseBridgeScale" : -0.05042474,
    "noseTipScale" : -0.004387415,
    "chinScale" : -0.1540687,
    "cheekOffsetY" : -0.000140416,
    "eyeWidth" : -0.04407183,
    "jawWidth" : -0.05124991,
    "animation" : 4,
    "isCommander" : true,
    "skinToneId" : "Skin_01",
    "eyeColorId" : "Eye_02",
    "hairRootId" : "Hair_04",
    "hairTipId" : "Hair_04",
    "tattooColorId" : "Tattoo_05",
    "lipColorId" : "Lip_01",
    "customPortraitSaveVersion" : 0
}
