{
    "Description" : {
        "Id" : "pilot_at_plato_p",
        "Name" : "pilot_at_plato_p",
        "Details" : "Random",
        "Icon" : "pilot_at_plato_p"
    },
    "ID" : "pilot_at_plato_p",
    "backgroundColor" : {
        "r" : 0,
        "g" : 0,
        "b" : 0,
        "a" : 0
    },
    "headMesh" : 0.5,
    "hairMesh" : 6,
    "beardMesh" : 0,
    "suitMesh" : 1,
    "scar" : 7,
    "lightRig" : 0,
    "cameraPosition" : 0,
    "complexionTex" : 1,
    "eyebrowTex" : 5,
    "tattooTex" : 7,
    "actualTattooTex" : 3,
    "weights" : [
        34.70969,
        15.13787,
        3.787615,
        31.65222,
        12.19379,
        2.51883
    ],
    "browOffsetY" : 0.00336703,
    "browOffsetZ" : 0.006092439,
    "noseBridgeScale" : -0.1037785,
    "noseTipScale" : 0.06661695,
    "chinScale" : -0.03637889,
    "cheekOffsetY" : -0.002128767,
    "eyeWidth" : 0.02146534,
    "jawWidth" : -0.007322204,
    "animation" : 3,
    "isCommander" : true,
    "skinToneId" : "Skin_06",
    "eyeColorId" : "Eye_05",
    "hairRootId" : "Hair_00",
    "hairTipId" : "Hair_00",
    "tattooColorId" : "Tattoo_04",
    "lipColorId" : "Lip_01",
    "customPortraitSaveVersion" : 0
}
