{
    "Description" : {
        "Id" : "Yangs_Evil_Twin",
        "Name" : "Yangs_Evil_Twin",
        "Details" : "Random",
        "Icon" : "Yangs_Evil_Twin"
    },
    "ID" : "Yangs_Evil_Twin",
    "backgroundColor" : {
        "r" : 0,
        "g" : 0,
        "b" : 0,
        "a" : 0
    },
    "headMesh" : 0.5,
    "hairMesh" : 14,
    "beardMesh" : 0,
    "suitMesh" : 0,
    "scar" : 0,
    "lightRig" : 2,
    "cameraPosition" : 3,
    "complexionTex" : 0,
    "eyebrowTex" : 2,
    "tattooTex" : 3,
    "actualTattooTex" : 0,
    "weights" : [
        12.10716,
        17.04206,
        3.569374,
        38.35074,
        21.79001,
        7.140656
    ],
    "browOffsetY" : -0.005799971,
    "browOffsetZ" : -0.0002880265,
    "noseBridgeScale" : -0.03226716,
    "noseTipScale" : -0.1843165,
    "chinScale" : -0.07488892,
    "cheekOffsetY" : 0.0004492908,
    "eyeWidth" : -0.01070285,
    "jawWidth" : -0.08923867,
    "animation" : 1,
    "isCommander" : true,
    "skinToneId" : "Skin_01",
    "eyeColorId" : "Eye_00",
    "hairRootId" : "Hair_00",
    "hairTipId" : "Hair_00",
    "tattooColorId" : "Tattoo_05",
    "lipColorId" : "Lip_01",
    "customPortraitSaveVersion" : 0
}
